{
  "0":
  {
    "lat" : "39.744416",
    "lng":"37.016162",
    "zoom":"6"
  },
  "1":
  {
    "lat" : "36.814152",
    "lng":"34.641233",
    "zoom":"8"
  },
  "2":
  {
    "lat" : "39.759057",
    "lng":"37.009743",
    "zoom":"6"
  },
  "3":
  {
    "lat" : "41.203518",
    "lng":"29.072729",
    "zoom":"6"
  },
  "4":
  {
    "lat" : "41.059497",
    "lng":"29.03557",
    "zoom":"8"
  },
  "5":
  {
    "lat" : "51.523437",
    "lng":"-0.040500",
    "zoom":"4"
  },
  "6":
  {
    "lat" : "37.4440259",
    "lng":"-122.1633045",
    "zoom":"14"
  },
  "7":{
    "lat": "36.8969",
    "lng": "30.7133",
    "zoom": "6"

  }
}
